.gitignore
LICENSE.txt
MANIFEST.in
README.md
eu_logo.jpg
hbp_archive.py
requirements.txt
setup.py
tests.py
docs/Makefile
docs/conf.py
docs/index.rst
docs/make.bat
hbp_archive.egg-info/PKG-INFO
hbp_archive.egg-info/SOURCES.txt
hbp_archive.egg-info/dependency_links.txt
hbp_archive.egg-info/requires.txt
hbp_archive.egg-info/top_level.txt