Metadata-Version: 2.1
Name: hbp-archive
Version: 1.0.0
Summary: A high-level API for interacting with the Human Brain Project archival storage at CSCS
Home-page: https://github.com/HumanBrainProject/hbp_archive
Author: Andrew P. Davison (CNRS), Shailesh Appukuttan (CNRS), Eszter Agnes Papp (University of Oslo)
Author-email: andrew.davison@cnrs.fr
License: UNKNOWN
Keywords: swift hbp cscs data
Platform: UNKNOWN
Classifier: Development Status :: 4 - Beta
Classifier: Intended Audience :: Science/Research
Classifier: Topic :: Scientific/Engineering
Classifier: License :: OSI Approved :: Apache Software License
Classifier: Programming Language :: Python :: 2
Classifier: Programming Language :: Python :: 2.7
Classifier: Programming Language :: Python :: 3
Classifier: Programming Language :: Python :: 3.4
Classifier: Programming Language :: Python :: 3.5
Classifier: Programming Language :: Python :: 3.6
Classifier: Programming Language :: Python :: 3.7
